aio_azure_clients_toolbox/__init__.py
aio_azure_clients_toolbox/connection_pooling.py
aio_azure_clients_toolbox/clients/__init__.py
aio_azure_clients_toolbox/clients/azure_blobs.py
aio_azure_clients_toolbox/clients/cosmos.py
aio_azure_clients_toolbox/clients/eventgrid.py
aio_azure_clients_toolbox/clients/eventhub.py
aio_azure_clients_toolbox/clients/service_bus.py
aio_azure_clients_toolbox/clients/types.py
aio_azure_clients_toolbox/testing_utils/__init__.py
aio_azure_clients_toolbox/testing_utils/fixtures.py
aio_azure_clients_toolbox-1.0.5.dist-info/licenses/LICENSE
scripts/eventhub_validate.py
scripts/service_bus_validate.py
tests/conftest.py
tests/test_connection_pooling.py
tests/clients/test_azure_blobs.py
tests/clients/test_cosmos.py
tests/clients/test_eventgrid.py
tests/clients/test_eventhub.py
tests/clients/test_service_bus.py
aio_azure_clients_toolbox-1.0.5.dist-info/METADATA
aio_azure_clients_toolbox-1.0.5.dist-info/WHEEL
aio_azure_clients_toolbox-1.0.5.dist-info/top_level.txt
aio_azure_clients_toolbox-1.0.5.dist-info/RECORD
