Metadata-Version: 2.4
Name: aio-azure-clients-toolbox
Version: 1.0.5
Summary: Async Azure Clients Mulligan Python projects
Author-email: Erik Aker <eaker@mulliganfunding.com>
License:                                  Apache License
Project-URL: Repository, https://github.com/MulliganFunding/aio-azure-clients-toolbox
Project-URL: Documentation, https://mulliganfunding.github.io/aio-azure-clients-toolbox
Project-URL: Releases, https://github.com/MulliganFunding/aio-azure-clients-toolbox/releases
Requires-Python: >=3.11
License-File: LICENSE
Requires-Dist: aiofiles
Requires-Dist: aiohttp
Requires-Dist: anyio
Requires-Dist: azure-core-tracing-opentelemetry
Requires-Dist: azure-cosmos
Requires-Dist: azure-eventgrid
Requires-Dist: azure-eventhub
Requires-Dist: azure-identity
Requires-Dist: azure-servicebus
Requires-Dist: azure-storage-blob
Dynamic: license-file
